python_configuration_wrapper/__init__.py
python_configuration_wrapper-1.2.0.dist-info/METADATA
python_configuration_wrapper-1.2.0.dist-info/WHEEL
python_configuration_wrapper-1.2.0.dist-info/top_level.txt
python_configuration_wrapper-1.2.0.dist-info/RECORD
