Metadata-Version: 2.1
Name: python-configuration-wrapper
Version: 1.2.0
Summary: A wrapper of python-configuration
Home-page: https://github.com/pletessier/python-configuration-wrapper
Author: Pierre Letessier
License: UNKNOWN
Keywords: configuration
Platform: UNKNOWN
Requires-Dist: python-configuration[toml,yaml] (~=0.6)
Requires-Dist: singleton (~=0.1)
Requires-Dist: dotmap (~=1.3)
